projetaai_azure/__init__.py
projetaai_azure/cli/__init__.py
projetaai_azure/cli/credential.py
projetaai_azure/cli/pipeline.py
projetaai_azure/cli/run.py
projetaai_azure/converters/__init__.py
projetaai_azure/converters/config.py
projetaai_azure/converters/create_batch_endpoint.py
projetaai_azure/converters/create_batch_pipeline.py
projetaai_azure/converters/create_datastore_trigger.py
projetaai_azure/converters/create_realtime_endpoint.py
projetaai_azure/converters/environment.py
projetaai_azure/converters/job_creator.py
projetaai_azure/converters/pipeline_converter.py
projetaai_azure/converters/publisher.py
projetaai_azure/converters/run.py
projetaai_azure/converters/scheduler.py
projetaai_azure/converters/setup.py
projetaai_azure/converters/step.py
projetaai_azure/plugin.py
projetaai_azure/runners/__init__.py
projetaai_azure/runners/config_loader.py
projetaai_azure/runners/databricks.py
projetaai_azure/runners/datastore.py
projetaai_azure/runners/injector.py
projetaai_azure/runners/keyvault.py
projetaai_azure/utils/__init__.py
projetaai_azure/utils/constants.py
projetaai_azure/utils/io.py
projetaai_azure/utils/iterable.py
projetaai_azure/utils/other.py
projetaai_azure/utils/pipeline.py
projetaai_azure/utils/string.py
projetaai_azure/utils/typing.py
projetaai_azure-0.1.0b0.dist-info/entry_points.txt
projetaai_azure-0.1.0b0.dist-info/WHEEL
projetaai_azure-0.1.0b0.dist-info/METADATA
projetaai_azure-0.1.0b0.dist-info/RECORD
